py_path_signature/__init__.py
py_path_signature/data_models/basic.py
py_path_signature/data_models/error_messages.py
py_path_signature/data_models/stroke.py
py_path_signature/path_signature_extractor.py
py_path_signature-210927.5.dist-info/LICENSE
py_path_signature-210927.5.dist-info/WHEEL
py_path_signature-210927.5.dist-info/METADATA
py_path_signature-210927.5.dist-info/RECORD
