Metadata-Version: 2.1
Name: py-path-signature
Version: 210927.5
Summary: 
Author: TBD
Author-email: tbd@example.com
Requires-Python: >=3.8,<4.0
Classifier: Programming Language :: Python :: 3
Classifier: Programming Language :: Python :: 3.8
Classifier: Programming Language :: Python :: 3.9
Requires-Dist: numpy (>=1.21.1,<2.0.0)
Requires-Dist: pydantic (>=1.8.2,<2.0.0)
